qgofer/__init__.py
qgofer/__main__.py
qgofer/app.py
qgofer/cli.py
qgofer/logger.py
qgofer/rake.py
qgofer/utils.py
qgofer-0.0.2.dist-info/LICENSE
qgofer-0.0.2.dist-info/entry_points.txt
qgofer-0.0.2.dist-info/WHEEL
qgofer-0.0.2.dist-info/METADATA
qgofer-0.0.2.dist-info/RECORD
